medmolnet/__init__.py
medmolnet/mmn.py
medmolnet-1.0.4.dist-info/LICENSE
medmolnet-1.0.4.dist-info/METADATA
medmolnet-1.0.4.dist-info/WHEEL
medmolnet-1.0.4.dist-info/top_level.txt
medmolnet-1.0.4.dist-info/RECORD
