Metadata-Version: 2.1
Name: medmolnet
Version: 1.0.4
Summary: create sub networks
Home-page: https://github.com/Tohar-Ts/Towards-personalized-medicine-in-cancer
Author: Tohar&Ayelet
Author-email: Toharbk@gmail.com
Project-URL: Bug Tracker, https://github.com/Tohar-Ts/Towards-personalized-medicine-in-cancer/issues
Classifier: Programming Language :: Python :: 3
Classifier: License :: OSI Approved :: MIT License
Classifier: Operating System :: OS Independent
Requires-Python: >=3.6
License-File: LICENSE
Requires-Dist: networkx
Requires-Dist: pandas
Requires-Dist: xlsxwriter
Requires-Dist: requests
Requires-Dist: patool
Requires-Dist: psycopg2
Requires-Dist: configparser
Requires-Dist: pyvis
Requires-Dist: numpy
